{"cameraMode":{"drawMode":0,"name":"Shaded","section":"Shading Mode"},"sceneLighting":true,"audioPlay":false,"sceneViewState":{"showFog":true,"showMaterialUpdate":false,"showSkybox":true,"showFlares":true,"showImageEffects":true,"showParticleSystems":true},"in2DMode":false,"pivot":{"x":13.936269760131836,"y":-3.873650074005127,"z":16.030349731445314},"rotation":{"x":0.09431260079145432,"y":0.5249471068382263,"z":-0.058684878051280978,"w":0.8438629508018494},"size":9.699999809265137,"orthographic":false}